runtexts/__init__.py
runtexts/cli.py
runtexts-1.7.dist-info/LICENSE
runtexts-1.7.dist-info/METADATA
runtexts-1.7.dist-info/WHEEL
runtexts-1.7.dist-info/entry_points.txt
runtexts-1.7.dist-info/top_level.txt
runtexts-1.7.dist-info/RECORD
