Metadata-Version: 2.1
Name: runtexts
Version: 1.7
Summary: A CLI and GUI tool to send automated messages.
Home-page: https://github.com/iamovi/project_runtexts
Author: Maruf Ovi
Author-email: fornet.ovi@gmail.com
License: MIT
Keywords: automation,messaging,CLI,pyautogui,tkinter,GUI
Requires-Python: >=3.6
License-File: LICENSE
Requires-Dist: pyautogui
Requires-Dist: colorama
Requires-Dist: requests
Requires-Dist: keyboard
